{"web":{"client_id":"755176835338-1uleopc2rpbe0op3fd299bp4j823graq.apps.googleusercontent.com","project_id":"byoo-af7e5","auth_uri":"https://accounts.google.com/o/oauth2/auth","token_uri":"https://oauth2.googleapis.com/token","auth_provider_x509_cert_url":"https://www.googleapis.com/oauth2/v1/certs","client_secret":"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","redirect_uris":["https://byoo.com.ar/__/auth/handler","http://localhost:3000/__/auth/handler","https://www.byoo.com.ar/__/auth/handler"],"javascript_origins":["https://byoo.com.ar","http://localhost:3000"]}}